v4l2ctl/__init__.py
v4l2ctl/v4l2device.py
v4l2ctl/v4l2format.py
v4l2ctl/v4l2frame.py
v4l2ctl/v4l2types.py
v4l2ctl/ioctls/__init__.py
v4l2ctl/ioctls/ioctlmacros.py
v4l2ctl/ioctls/v4l2ioctl.py
v4l2ctl/ioctls/v4l2ioctlenums.py
v4l2ctl/ioctls/v4l2ioctlstructs.py
v4l2ctl/utils/__init__.py
v4l2ctl/utils/enumcontainer.py
v4l2ctl/utils/filehandle.py
v4l2ctl-0.1a5.dist-info/LICENSE
v4l2ctl-0.1a5.dist-info/METADATA
v4l2ctl-0.1a5.dist-info/WHEEL
v4l2ctl-0.1a5.dist-info/top_level.txt
v4l2ctl-0.1a5.dist-info/RECORD
