Metadata-Version: 2.1
Name: v4l2ctl
Version: 0.1a5
Summary: Python package to control V4l2 drivers
Home-page: https://github.com/MichaelIsrael/v4l2ctl
Author: Michael Israel
Author-email: mich.m.israel@gmail.com
License: European Union Public Licence 1.2 (EUPL 1.2)
Platform: Linux
Classifier: License :: OSI Approved :: European Union Public Licence 1.2 (EUPL 1.2)
Classifier: Programming Language :: Python :: 3
Classifier: Operating System :: POSIX :: Linux
Classifier: Topic :: Multimedia :: Video
Classifier: Topic :: Software Development :: Libraries
Classifier: Development Status :: 3 - Alpha
Requires-Python: >=3.6
